posetree/__init__.py
posetree/pose.py
posetree-1.1.2.dist-info/LICENSE
posetree-1.1.2.dist-info/METADATA
posetree-1.1.2.dist-info/WHEEL
posetree-1.1.2.dist-info/top_level.txt
posetree-1.1.2.dist-info/RECORD
