Metadata-Version: 2.1
Name: posetree
Version: 1.1.2
Summary: A Python library doing pose math for robotics.
Author-email: Benjie Holson <bmholson@gmail.com>
Project-URL: homepage, https://github.com/robobenjie/posetree
Project-URL: documentation, https://htmlpreview.github.io/?https://raw.githubusercontent.com/robobenjie/posetree/main/docs/posetree/pose.html
Project-URL: repository, https://github.com/robobenjie/posetree
Project-URL: changelog, https://github.com/robobenjie/posetree/releases
Classifier: Development Status :: 4 - Beta
Classifier: Intended Audience :: Developers
Classifier: Topic :: Scientific/Engineering
Classifier: License :: OSI Approved :: MIT License
Classifier: Programming Language :: Python :: 3
License-File: LICENSE
Requires-Dist: numpy>=1.21.2
Requires-Dist: scipy>=1.7.1
